{
	"vJarl" : {
		"affinity" : "might",
		"mapObject" : { "templates" : { "default" : { "animation" : "classes/jarl/AH10_.def", "editorAnimation": "classes/jarl/AH10_E.def" } } },
		"animation":  { "battle" : { "male" : "classes/jarl/CH010.DEF",  "female" : "classes/jarl/CH010.DEF" }},
		"commander" : "",
		"defaultTavern" : 5,
		"faction" : "vVori",
		"highLevelChance" : { "attack" : 60, "defence" : 30, "knowledge" : 5, "spellpower" : 5 },
		"lowLevelChance" : { "attack" : 50, "defence" : 20, "knowledge" : 15, "spellpower" : 15 },
		"name" : "Jarl",
		"primarySkills" : { "attack" : 4, "defence" : 1, "knowledge" : 0, "spellpower" : 1 },
		"secondarySkills" : {
			"airMagic" : 4,
			"archery" : 7,
			"armorer" : 7,
			"artillery" : 6,
			"ballistics" : 5,
			"diplomacy" : 2,
			"eagleEye" : 6,
			"earthMagic" : 5,
			"estates" : 7,
			"fireMagic" : 2,
			"intelligence" : 3,
			"leadership" : 6,
			"learning" : 5,
			"logistics" : 3,
			"luck" : 6,
			"mysticism" : 4,
			"navigation" : 9,
			"necromancy" : 2,
			"offence" : 7,
			"pathfinding" : 7
			"resistance" : 4,
			"scholar" : 4,
			"scouting" : 8,
			"sorcery" : 2,
			"tactics" : 5,
			"waterMagic" : 9,
			"wisdom" : 4,
			"firstAid" : 8
		},
		"tavern" : {
			"castle" : 5,
			"conflux" : 3,
			"dungeon" : 5,
			"fortress" : 4,
			"inferno" : 4,
			"necropolis" : 2,
			"rampart" : 6,
			"stronghold" : 6,
			"tower" : 6
		}
	}
}
